replace_pip_with_uv_pip.py
replace_pip_with_uv_pip-0.0.1.dist-info/METADATA
replace_pip_with_uv_pip-0.0.1.dist-info/WHEEL
replace_pip_with_uv_pip-0.0.1.dist-info/entry_points.txt
replace_pip_with_uv_pip-0.0.1.dist-info/top_level.txt
replace_pip_with_uv_pip-0.0.1.dist-info/RECORD
