Metadata-Version: 2.1
Name: replace-pip-with-uv-pip
Version: 0.0.1
Summary: Replace pip with uv pip.
Project-URL: Homepage, https://github.com/njzjz/replace-pip-with-uv-pip
Classifier: Programming Language :: Python
Classifier: Programming Language :: Python :: 3
Requires-Python: >=3.8
Requires-Dist: uv
